Metadata-Version: 1.1
Name: lpocv
Version: 0.0.2
Summary: Leave-pair-out cross-validation
Home-page: http://github.com/mauliknariya/lpocv
Author: Maulik Nariya
Author-email: mauliknariya@gmail.com
License: UNKNOWN
Keywords: leave-pair-out,cross-validation,batch effects,bioinformatics
Platform: UNKNOWN
Classifier: Development Status :: 3 - Alpha
Classifier: Intended Audience :: Science/Research
Classifier: License :: OSI Approved :: MIT License
Classifier: Natural Language :: English
Classifier: Operating System :: OS Independent
Classifier: Programming Language :: Python :: 3
Classifier: Topic :: Scientific/Engineering :: Bio-Informatics
